pysimexport/__init__.py
pysimexport/core.py
pysimexport-0.1.8.dist-info/LICENCE
pysimexport-0.1.8.dist-info/METADATA
pysimexport-0.1.8.dist-info/WHEEL
pysimexport-0.1.8.dist-info/top_level.txt
pysimexport-0.1.8.dist-info/RECORD
