Metadata-Version: 2.1
Name: pysimexport
Version: 0.1.8
Summary: A Python package to export simulation data
Home-page: https://github.com/vincentchoqueuse/pysimexport
Author: Vincent Choqueuse
Author-email: vincent.choqueuse@gmail.com
License: BSD 2-clause
Platform: UNKNOWN
Classifier: Intended Audience :: Science/Research
Classifier: License :: OSI Approved :: BSD License
Classifier: Programming Language :: Python :: 3
License-File: LICENCE
Requires-Dist: numpy (>=1.20)
Requires-Dist: boto3 (>=1.16)
